mariadb_vector/__init__.py
mariadb_vector/functions.py
mariadb_vector/vector.py
mariadb_vector-0.3.0.dist-info/licenses/LICENSE
mariadb_vector-0.3.0.dist-info/METADATA
mariadb_vector-0.3.0.dist-info/WHEEL
mariadb_vector-0.3.0.dist-info/top_level.txt
mariadb_vector-0.3.0.dist-info/RECORD
