Metadata-Version: 2.4
Name: mariadb-vector
Version: 0.3.0
Summary: Integrate MariaDB's VECTOR type with SQL Alchemy and SQL Model
Author-email: heonjin <kwonhj9416@gmail.com>
Maintainer-email: heonjin <kwonhj9416@gmail.com>
License: MIT
Project-URL: Documentation, https://github.com/kwon-evan/mariadb-vector?tab=readme-ov-file#usage
Project-URL: Repository, https://github.com/kwon-evan/mariadb-vector.git
Project-URL: Issues, https://github.com/kwon-evan/mariadb-vector/issues
Keywords: mariadb,vector,sql,sqlalchemy,sqlmodel
Classifier: Programming Language :: Python :: 3
Classifier: Programming Language :: Python :: 3.10
Classifier: Programming Language :: Python :: 3.11
Classifier: Programming Language :: Python :: 3.12
Requires-Python: >=3.10
License-File: LICENSE
Requires-Dist: sqlalchemy>=2.0.37
Dynamic: license-file
